{
  "unversionedId": "WhatsNext",
  "id": "WhatsNext",
  "title": "What's next ?",
  "description": "Now you have a runnable GAMA on your computer, and you know a bit more about how to use the platform, you are ready to navigate through the website. Use the new powerful functionnalities of the website :",
  "source": "@site/../docs/WhatsNext.md",
  "sourceDirName": ".",
  "slug": "/WhatsNext",
  "permalink": "/docs/WhatsNext",
  "draft": false,
  "tags": [],
  "version": "current",
  "lastUpdatedBy": "Author",
  "lastUpdatedAt": 1539502055,
  "formattedLastUpdatedAt": "10/14/2018",
  "frontMatter": {
    "title": "What's next ?"
  }
}