{
  "unversionedId": "Multicriteria decision Multicriteria",
  "id": "version-1.8.1/Multicriteria decision Multicriteria",
  "title": "Multicriteria",
  "description": "[//]: # (keyword|operator_^)",
  "source": "@site/versioned_docs/version-1.8.1/Multicriteria decision Multicriteria.md",
  "sourceDirName": ".",
  "slug": "/Multicriteria decision Multicriteria",
  "permalink": "/docs/Multicriteria decision Multicriteria",
  "draft": false,
  "tags": [],
  "version": "1.8.1",
  "lastUpdatedBy": "Author",
  "lastUpdatedAt": 1539502055,
  "formattedLastUpdatedAt": "10/14/2018",
  "frontMatter": {
    "title": "Multicriteria",
    "id": "Multicriteria decision Multicriteria",
    "original_id": "Multicriteria decision Multicriteria"
  }
}