{
  "unversionedId": "CoModelingTutorial",
  "id": "version-1.8.1/CoModelingTutorial",
  "title": "Co-modeling tutorial",
  "description": "This tutorial introduces the co-modeling feature offered by GAMA.",
  "source": "@site/versioned_docs/version-1.8.1/CoModelingTutorial.md",
  "sourceDirName": ".",
  "slug": "/CoModelingTutorial",
  "permalink": "/docs/CoModelingTutorial",
  "draft": false,
  "tags": [],
  "version": "1.8.1",
  "lastUpdatedBy": "Author",
  "lastUpdatedAt": 1539502055,
  "formattedLastUpdatedAt": "10/14/2018",
  "frontMatter": {
    "title": "Co-modeling tutorial",
    "id": "CoModelingTutorial",
    "original_id": "CoModelingTutorial"
  }
}